{"options":{"collation":{"maxVariable":"punct","normalization":false,"locale":"en","caseLevel":false,"strength":{"$numberInt":"3"},"numericOrdering":false,"alternate":"non-ignorable","caseFirst":"off","backwards":false,"version":"57.1"}},"indexes":[{"v":{"$numberInt":"2"},"key":{"_id":{"$numberInt":"1"}},"name":"_id_","collation":{"locale":"en","caseLevel":false,"caseFirst":"off","strength":{"$numberInt":"3"},"numericOrdering":false,"alternate":"non-ignorable","maxVariable":"punct","normalization":false,"backwards":false,"version":"57.1"}},{"v":{"$numberInt":"2"},"key":{"LanguageId":{"$numberInt":"1"},"ResourceName":{"$numberInt":"1"}},"name":"Language","collation":{"locale":"en","caseLevel":false,"caseFirst":"off","strength":{"$numberInt":"3"},"numericOrdering":false,"alternate":"non-ignorable","maxVariable":"punct","normalization":false,"backwards":false,"version":"57.1"}},{"v":{"$numberInt":"2"},"key":{"ResourceName":{"$numberInt":"1"}},"name":"ResourceName","collation":{"locale":"en","caseLevel":false,"caseFirst":"off","strength":{"$numberInt":"3"},"numericOrdering":false,"alternate":"non-ignorable","maxVariable":"punct","normalization":false,"backwards":false,"version":"57.1"}}],"uuid":"68ad79920425479f923eaed51e312220","collectionName":"LocaleStringResource","type":"collection"}